odoo/addons/product_state_history/README.rst
odoo/addons/product_state_history/__init__.py
odoo/addons/product_state_history/__manifest__.py
odoo/addons/product_state_history/i18n/product_state_history.pot
odoo/addons/product_state_history/migrations/14.0.1.0.1/pre-migrate.py
odoo/addons/product_state_history/models/__init__.py
odoo/addons/product_state_history/models/product_state_history.py
odoo/addons/product_state_history/models/product_template.py
odoo/addons/product_state_history/models/report_product_state_history.py
odoo/addons/product_state_history/readme/CONTRIBUTORS.rst
odoo/addons/product_state_history/readme/DESCRIPTION.rst
odoo/addons/product_state_history/readme/USAGE.rst
odoo/addons/product_state_history/report/report_product_state_history.xml
odoo/addons/product_state_history/security/product_state_history.xml
odoo/addons/product_state_history/security/product_state_history_wizard.xml
odoo/addons/product_state_history/static/description/icon.png
odoo/addons/product_state_history/static/description/index.html
odoo/addons/product_state_history/tests/__init__.py
odoo/addons/product_state_history/tests/common.py
odoo/addons/product_state_history/tests/test_product_state_history.py
odoo/addons/product_state_history/views/product_state_history.xml
odoo/addons/product_state_history/views/product_template.xml
odoo/addons/product_state_history/wizards/__init__.py
odoo/addons/product_state_history/wizards/product_state_history_wizard.py
odoo/addons/product_state_history/wizards/product_state_history_wizard.xml
odoo14_addon_product_state_history-14.0.1.0.2.dist-info/METADATA
odoo14_addon_product_state_history-14.0.1.0.2.dist-info/WHEEL
odoo14_addon_product_state_history-14.0.1.0.2.dist-info/top_level.txt
odoo14_addon_product_state_history-14.0.1.0.2.dist-info/RECORD
